search/__init__.py
search/examples.py
search/fn.py
search/internals/__init__.py
search/internals/builtins.py
search/internals/fn.py
search/internals/messanger.py
search/internals/operators.py
search/internals/types.py
search/schemas/__init__.py
search/schemas/common_types.py
search/schemas/examples/__init__.py
search/schemas/examples/category.py
search/schemas/examples/chart.py
search/schemas/examples/domain.py
search/schemas/examples/layout.py
search/schemas/examples/location.py
search/schemas/examples/market_event.py
search/schemas/examples/person.py
search/schemas/examples/place.py
search/schemas/examples/tag.py
search/schemas/examples/views.py
search/schemas/raws/__init__.py
search/schemas/raws/category.py
search/schemas/raws/chart.py
search/schemas/raws/domain.py
search/schemas/raws/layout.py
search/schemas/raws/location.py
search/schemas/raws/market_event.py
search/schemas/raws/person.py
search/schemas/raws/place.py
search/schemas/raws/tag.py
search/schemas/sources/__init__.py
search/schemas/sources/category.py
search/schemas/sources/chart.py
search/schemas/sources/domain.py
search/schemas/sources/helpers.py
search/schemas/sources/layout.py
search/schemas/sources/location.py
search/schemas/sources/market_event.py
search/schemas/sources/person.py
search/schemas/sources/place.py
search/schemas/sources/tag.py
search/schemas/views.py
search/types.py
dep_search-3.0.1.dist-info/WHEEL
dep_search-3.0.1.dist-info/METADATA
dep_search-3.0.1.dist-info/RECORD
